spef_extractor/__init__.py
spef_extractor/__main__.py
spef_extractor/spef_extractor.py
spef_extractor/lef_def_parser/__init__.py
spef_extractor/lef_def_parser/def_parser.py
spef_extractor/lef_def_parser/def_util.py
spef_extractor/lef_def_parser/lef_parser.py
spef_extractor/lef_def_parser/lef_util.py
spef_extractor/lef_def_parser/util.py
spef_extractor-0.2.1.dist-info/AUTHORS.md
spef_extractor-0.2.1.dist-info/LICENSE
spef_extractor-0.2.1.dist-info/METADATA
spef_extractor-0.2.1.dist-info/WHEEL
spef_extractor-0.2.1.dist-info/entry_points.txt
spef_extractor-0.2.1.dist-info/top_level.txt
spef_extractor-0.2.1.dist-info/RECORD
