Metadata-Version: 2.1
Name: spef-extractor
Version: 0.2.1
Summary: A parasitics estimator based on layout and technology files.
Home-page: UNKNOWN
Author: Mohamed Gaber
Author-email: mohamed.gaber@aucegypt.edu
License: UNKNOWN
Platform: UNKNOWN
Classifier: Programming Language :: Python :: 3
Classifier: Intended Audience :: Developers
Classifier: Operating System :: OS Independent
Requires-Python: >3.6
License-File: LICENSE
License-File: AUTHORS.md
Requires-Dist: numpy (>=1.15)
Requires-Dist: sympy (>=1.9)
Requires-Dist: matplotlib (>=3.3.4)
